rtl/data_ram.v
module data_ram(
    input clk,
    input we,
    input [31:0] addr,
    input [31:0] din,
    output [31:0] dout
);

    reg [31:0] mem [0:255];

    initial begin
        $readmemh("mem/data.hex", mem);
    end

    assign dout = mem[addr[7:0]];

    always @(posedge clk) begin
        if (we)
            mem[addr[7:0]] <= din;
    end

endmodule

rtl/control_unit.v
module control_unit(
    input clk,
    input reset,
    input [4:0] opcode,
    input zero_flag,
    input neg_flag,

    output reg ir_load,
    output reg pc_inc,
    output reg pc_load,
    output reg reg_write,
    output reg flag_write,
    output reg [3:0] alu_op,
    output reg state_fetch,
    output reg state_decode,
    output reg state_execute,
    output reg state_writeback,
    output reg halted,
    output reg mem_write
);

reg [1:0] state;
reg [1:0] next_state;

localparam FETCH     = 2'b00;
localparam DECODE    = 2'b01;
localparam EXECUTE   = 2'b10;
localparam WRITEBACK = 2'b11;

always @(posedge clk or posedge reset) begin
    if (reset)
        state <= FETCH;
    else
        state <= next_state;
end

always @(*) begin
    case (state)
        FETCH:     next_state = DECODE;
        DECODE:    next_state = EXECUTE;
        EXECUTE:   next_state = (opcode == 5'b11111) ? EXECUTE : WRITEBACK;
        WRITEBACK: next_state = FETCH;
        default:   next_state = FETCH;
    endcase
end

always @(*) begin
    ir_load         = 1'b0;
    pc_inc          = 1'b0;
    pc_load         = 1'b0;
    reg_write       = 1'b0;
    flag_write      = 1'b0;
    alu_op          = 4'b0000;
    state_fetch     = 1'b0;
    state_decode    = 1'b0;
    state_execute   = 1'b0;
    state_writeback = 1'b0;
    halted          = 1'b0;
    mem_write      = 1'b0;

    case (state)
        FETCH: begin
            state_fetch = 1'b1;
            ir_load     = 1'b1;
        end

        DECODE: begin
            state_decode = 1'b1;
            pc_inc       = 1'b1;
        end

        EXECUTE: begin
            state_execute = 1'b1;

            case (opcode)
                5'b00000: begin // LDI
                    reg_write = 1'b1;
                end

                5'b00001: begin // MOV
                    reg_write = 1'b1;
                end

                5'b00010: begin // ADD
                    alu_op     = 4'b0000;
                    flag_write = 1'b1;
                    reg_write  = 1'b1;
                end

                5'b00011: begin // SUB
                    alu_op     = 4'b0001;
                    flag_write = 1'b1;
                    reg_write  = 1'b1;
                end

                5'b00100: begin // AND
                    alu_op     = 4'b0010;
                    flag_write = 1'b1;
                    reg_write  = 1'b1;
                end

                5'b00101: begin // OR
                    alu_op     = 4'b0011;
                    flag_write = 1'b1;
                    reg_write  = 1'b1;
                end

                5'b00110: begin // XOR
                    alu_op     = 4'b0100;
                    flag_write = 1'b1;
                    reg_write  = 1'b1;
                end

                5'b00111: begin // CMP (SUB, nur Flags setzen)
                    alu_op     = 4'b0001;
                    flag_write = 1'b1;
                end

                5'b01000: begin // JMP
                    pc_load = 1'b1;
                end

                5'b01001: begin // JZ
                    if (zero_flag)
                        pc_load = 1'b1;
                end

                5'b01010: begin // SHL
                    alu_op     = 4'b0110;
                    flag_write = 1'b1;
                    reg_write  = 1'b1;
                end

                5'b01011: begin // SHR
                    alu_op     = 4'b0111;
                    flag_write = 1'b1;
                    reg_write  = 1'b1;
                end

                5'b01100: begin // SRA
                    alu_op     = 4'b1000;
                    flag_write = 1'b1;
                    reg_write  = 1'b1;
                end

                5'b01101: begin // NEG
                    alu_op     = 4'b1001;
                    flag_write = 1'b1;
                    reg_write  = 1'b1;
                end

                5'b01110: begin // MUL
                    alu_op    = 4'b1010;
                    reg_write = 1'b1;
                end

                5'b01111: begin // NOT
                    alu_op     = 4'b0101;
                    flag_write = 1'b1;
                    reg_write  = 1'b1;
                end

                5'b10000: begin // JN
                    if (neg_flag)
                        pc_load = 1'b1;
                end

                5'b10001: begin // LOAD
                    reg_write = 1'b1;
                end

                5'b10010: begin // STORE
                    mem_write = 1'b1;
                end

                5'b11111: begin // HALT
                    halted = 1'b1;
                end

                default: begin
                end
            endcase
        end

        WRITEBACK: begin
            state_writeback = 1'b1;
        end
    endcase
end

endmodule

rtl/alu.v

module alu(
    input [31:0] a, b,
    input [3:0] op,
    output reg [31:0] result,
    output reg zero, carry, negative
);

always @(*) begin
    result   = 32'h0;
    carry    = 1'b0;
    zero     = 1'b0;
    negative = 1'b0;
  case (op)
    4'b0000: {carry, result} = a + b;           // ADD
    4'b0001: {carry, result} = a - b;           // SUB
    4'b0010: result = a & b;                    // AND
    4'b0011: result = a | b;                    // OR
    4'b0100: result = a ^ b;                    // XOR
    4'b0101: result = ~a;                       // NOT
    4'b0110: result = a << b[4:0];              // SHL
    4'b0111: result = a >> b[4:0];              // SHR (logical)
    4'b1000: result = $signed(a) >>> b[4:0];    // SRA (arithmetic)
    4'b1001: result = ~a + 32'h1;              // NEG
    4'b1010: result = a * b;                    // MUL (lower 32-bit)
    default: begin
     result = 32'h0;
     carry = 1'b0;
     zero = 1'b0;
    end
  endcase
  zero     = ~| result;
  negative = result[31];

end


endmodule

rtl/register.v
module register(
    input clk,
    input reset, // async reset
    input we, // write enabled
    input [31:0] d,
    output reg [31:0] q
);

    always @(posedge clk or posedge reset) begin
        if(reset) q<=32'h0;
        else if (we) q<=d;
    end

endmodule

rtl/regfile.v
module regfile (
    input clk,
    input reset,  //asny reset 
    input we,
    input [1:0] wa, // write adreess
    input [31:0] wd, // write data
    input [1:0] ra1, // read address 1
    input [1:0] ra2, // read address 2
    output reg [31:0] rd1, // read data 1
    output reg [31:0] rd2 // read data
);

    wire [31:0] q0, q1, q2, q3;
    wire we0, we1, we2, we3;

    assign we0 = we & (wa == 2'b00);
    assign we1 = we & (wa == 2'b01);
    assign we2 = we & (wa == 2'b10);
    assign we3 = we & (wa == 2'b11);

    register reg0 (.clk(clk), .reset(reset), .we(we0), .d(wd), .q(q0));
    register reg1 (.clk(clk), .reset(reset), .we(we1), .d(wd), .q(q1));
    register reg2 (.clk(clk), .reset(reset), .we(we2), .d(wd), .q(q2));
    register reg3 (.clk(clk), .reset(reset), .we(we3), .d(wd), .q(q3));

    always @(*) begin
        case (ra1)
            2'b00: rd1 = q0;
            2'b01: rd1 = q1;
            2'b10: rd1 = q2;
            2'b11: rd1 = q3;
        endcase
    end

    always @(*) begin
        case (ra2)
            2'b00: rd2 = q0;
            2'b01: rd2 = q1;
            2'b10: rd2 = q2;
            2'b11: rd2 = q3;
        endcase
    end

endmodule

rtl/decoder.v
// Instruction format (48-bit):
// [47:40] = {3'b0, opcode[4:0]}             — Byte 5
// [39:32] = {4'b0, rd[1:0], rs[1:0]}        — Byte 4
// [31:0]  = imm (32 bits)                   — Bytes 3-0
//
// Byte 4 detail: bits[39:36]=0, bits[35:34]=rd, bits[33:32]=rs
// Hex encoding: OO DD IIIIIIII  (12 hex digits, DD = (rd<<2)|rs)
module decoder(
    input  [47:0] instr,
    output [4:0] opcode,
    output [1:0] rd,
    output [1:0] rs,
    output [31:0] imm
);

assign opcode = instr[44:40];
assign rd     = instr[35:34];
assign rs     = instr[33:32];
assign imm    = instr[31:0];




endmodule

rtl/pc.v
module pc (
    input clk,
    input reset,
    input load,
    input inc,
    input [31:0] din, // data input
    output reg [31:0] q // data output
);


    always @(posedge clk or posedge reset) begin
        if(reset) q<=32'h0;
        else if(load) q<=din;
        else if(inc) q<=q+1;
    end


endmodule

rtl/cpu_top.v
module cpu_top (
    input clk,
    input reset
);

wire [31:0] pc_q;
reg  [47:0] ir;

wire [4:0] opcode;
wire [1:0] rd;
wire [1:0] rs;
wire [31:0] imm;

wire [31:0] reg_rd1;
wire [31:0] reg_rd2;

wire [31:0] alu_result;
wire [31:0] mem_dout;
wire alu_zero;
wire alu_carry;
wire alu_negative;

reg zero_flag;
reg carry_flag;
reg neg_flag;

wire ir_load;
wire pc_inc;
wire pc_load;
wire reg_write;
wire flag_write;
wire mem_write;
wire [3:0] alu_op;

reg [47:0] rom [0:11];

initial begin
    $readmemh("mem/program.hex", rom);
end




always @(posedge clk or posedge reset) begin
    if (reset)
        ir <= 48'h0;
    else if (ir_load)
        ir <= rom[pc_q];
end

pc pc0 (
    .clk(clk),
    .reset(reset),
    .load(pc_load),
    .inc(pc_inc),
    .din(imm),
    .q(pc_q)
);

decoder dec (
    .instr(ir),
    .opcode(opcode),
    .rd(rd),
    .rs(rs),
    .imm(imm)
);

regfile rf0 (
    .clk(clk),
    .reset(reset),
    .we(reg_write),
    .wa(rd),
    .wd(write_data),
    .ra1(rd),
    .ra2(rs),
    .rd1(reg_rd1),
    .rd2(reg_rd2)
);

alu alu0 (
        .a(reg_rd1),
        .b(reg_rd2),
        .op(alu_op),
        .result(alu_result),
        .zero(alu_zero),
        .carry(alu_carry),
        .negative(alu_negative)
    );

control_unit cu0 (
    .clk(clk),
    .reset(reset),
    .opcode(opcode),
    .zero_flag(zero_flag),
    .neg_flag(neg_flag),
    .ir_load(ir_load),
    .pc_inc(pc_inc),
    .pc_load(pc_load),
    .reg_write(reg_write),
    .flag_write(flag_write),
    .alu_op(alu_op),
    .mem_write(mem_write),
    .state_fetch(),
    .state_decode(),
    .state_execute(),
    .state_writeback(),
    .halted()
);

// Register-indirekte Adressierung: bei LOAD/STORE kommt Adresse aus Rs (reg_rd2)
wire [31:0] ram_addr = ((opcode == 5'b10001) || (opcode == 5'b10010)) ? reg_rd2 : imm;

data_ram ram0 (
    .clk(clk),
    .we(mem_write),
    .addr(ram_addr),
    .din(reg_rd1),
    .dout(mem_dout)
);

reg [31:0] write_data;

always @(*) begin
    case (opcode)
        5'b00000: write_data = imm;         // LDI
        5'b00001: write_data = reg_rd2;     // MOV
        5'b00010: write_data = alu_result;  // ADD
        5'b00011: write_data = alu_result;  // SUB
        5'b00100: write_data = alu_result;  // AND
        5'b00101: write_data = alu_result;  // OR
        5'b00110: write_data = alu_result;  // XOR
        5'b01010: write_data = alu_result;  // SHL
        5'b01011: write_data = alu_result;  // SHR
        5'b01100: write_data = alu_result;  // SRA
        5'b01101: write_data = alu_result;  // NEG
        5'b01110: write_data = alu_result;  // MUL
        5'b01111: write_data = alu_result;  // NOT
        5'b10001: write_data = mem_dout;  // LOAD
        default:  write_data = 32'h0;
    endcase
end

always @(posedge clk or posedge reset) begin
        if (reset) begin
            zero_flag  <= 1'b0;
            carry_flag <= 1'b0;
            neg_flag   <= 1'b0;
        end
        else if (flag_write) begin
            zero_flag  <= alu_zero;
            carry_flag <= alu_carry;
            neg_flag   <= alu_negative;
        end
end

endmodule

tb/cpu_tb.v
`timescale 1ns/1ps

module cpu_tb;

// ─── DUT signals ──────────────────────────────────────────────────────────────
reg clk;
reg reset;

cpu_top dut (
    .clk   (clk),
    .reset (reset)
);

// ─── Clock: 10 ns period ──────────────────────────────────────────────────────
initial clk = 0;
always #5 clk = ~clk;

// Timeout nach 10000 ns
// initial begin
//     #100000;
//     $display("TIMEOUT: HALT nie erreicht");
//     $finish;
// end




initial begin
    $dumpfile("sim/waves/cpu_tb.vcd");
    $dumpvars(0, cpu_tb);

    // Reset
    reset = 1;
    #20;
    reset = 0;

    // Warte bis HALT
    @(posedge dut.cu0.halted);

    // Register ausgeben
    $display("R0: %d", dut.rf0.q0);
    $display("R1: %d", dut.rf0.q1);
    $display("R2: %d", dut.rf0.q2);
    $display("R3: %d", dut.rf0.q3);

    $finish;
end

endmodule

sim/waves/cpu_tb.vcd
$date
	Tue Mar 10 11:04:16 2026
$end
$version
	Icarus Verilog
$end
$timescale
	1ps
$end
$scope module cpu_tb $end
$var reg 1 ! clk $end
$var reg 1 " reset $end
$scope module dut $end
$var wire 1 ! clk $end
$var wire 1 " reset $end
$var wire 2 # rs [1:0] $end
$var wire 1 $ reg_write $end
$var wire 32 % reg_rd2 [31:0] $end
$var wire 32 & reg_rd1 [31:0] $end
$var wire 2 ' rd [1:0] $end
$var wire 32 ( ram_addr [31:0] $end
$var wire 32 ) pc_q [31:0] $end
$var wire 1 * pc_load $end
$var wire 1 + pc_inc $end
$var wire 5 , opcode [4:0] $end
$var wire 1 - mem_write $end
$var wire 32 . mem_dout [31:0] $end
$var wire 1 / ir_load $end
$var wire 32 0 imm [31:0] $end
$var wire 1 1 flag_write $end
$var wire 1 2 alu_zero $end
$var wire 32 3 alu_result [31:0] $end
$var wire 4 4 alu_op [3:0] $end
$var wire 1 5 alu_negative $end
$var wire 1 6 alu_carry $end
$var reg 1 7 carry_flag $end
$var reg 48 8 ir [47:0] $end
$var reg 1 9 neg_flag $end
$var reg 32 : write_data [31:0] $end
$var reg 1 ; zero_flag $end
$scope module alu0 $end
$var wire 4 < op [3:0] $end
$var wire 32 = b [31:0] $end
$var wire 32 > a [31:0] $end
$var reg 1 6 carry $end
$var reg 1 5 negative $end
$var reg 32 ? result [31:0] $end
$var reg 1 2 zero $end
$upscope $end
$scope module cu0 $end
$var wire 1 ! clk $end
$var wire 1 9 neg_flag $end
$var wire 1 " reset $end
$var wire 1 ; zero_flag $end
$var wire 5 @ opcode [4:0] $end
$var parameter 2 A DECODE $end
$var parameter 2 B EXECUTE $end
$var parameter 2 C FETCH $end
$var parameter 2 D WRITEBACK $end
$var reg 4 E alu_op [3:0] $end
$var reg 1 1 flag_write $end
$var reg 1 F halted $end
$var reg 1 / ir_load $end
$var reg 1 - mem_write $end
$var reg 2 G next_state [1:0] $end
$var reg 1 + pc_inc $end
$var reg 1 * pc_load $end
$var reg 1 $ reg_write $end
$var reg 2 H state [1:0] $end
$var reg 1 I state_decode $end
$var reg 1 J state_execute $end
$var reg 1 K state_fetch $end
$var reg 1 L state_writeback $end
$upscope $end
$scope module dec $end
$var wire 48 M instr [47:0] $end
$var wire 2 N rs [1:0] $end
$var wire 2 O rd [1:0] $end
$var wire 5 P opcode [4:0] $end
$var wire 32 Q imm [31:0] $end
$upscope $end
$scope module pc0 $end
$var wire 1 ! clk $end
$var wire 32 R din [31:0] $end
$var wire 1 + inc $end
$var wire 1 * load $end
$var wire 1 " reset $end
$var reg 32 S q [31:0] $end
$upscope $end
$scope module ram0 $end
$var wire 32 T addr [31:0] $end
$var wire 1 ! clk $end
$var wire 32 U dout [31:0] $end
$var wire 1 - we $end
$var wire 32 V din [31:0] $end
$upscope $end
$scope module rf0 $end
$var wire 1 ! clk $end
$var wire 2 W ra1 [1:0] $end
$var wire 2 X ra2 [1:0] $end
$var wire 1 " reset $end
$var wire 2 Y wa [1:0] $end
$var wire 32 Z wd [31:0] $end
$var wire 1 $ we $end
$var wire 1 [ we0 $end
$var wire 1 \ we1 $end
$var wire 1 ] we2 $end
$var wire 1 ^ we3 $end
$var wire 32 _ q3 [31:0] $end
$var wire 32 ` q2 [31:0] $end
$var wire 32 a q1 [31:0] $end
$var wire 32 b q0 [31:0] $end
$var reg 32 c rd1 [31:0] $end
$var reg 32 d rd2 [31:0] $end
$scope module reg0 $end
$var wire 1 ! clk $end
$var wire 32 e d [31:0] $end
$var wire 1 " reset $end
$var wire 1 [ we $end
$var reg 32 f q [31:0] $end
$upscope $end
$scope module reg1 $end
$var wire 1 ! clk $end
$var wire 32 g d [31:0] $end
$var wire 1 " reset $end
$var wire 1 \ we $end
$var reg 32 h q [31:0] $end
$upscope $end
$scope module reg2 $end
$var wire 1 ! clk $end
$var wire 32 i d [31:0] $end
$var wire 1 " reset $end
$var wire 1 ] we $end
$var reg 32 j q [31:0] $end
$upscope $end
$scope module reg3 $end
$var wire 1 ! clk $end
$var wire 32 k d [31:0] $end
$var wire 1 " reset $end
$var wire 1 ^ we $end
$var reg 32 l q [31:0] $end
$upscope $end
$upscope $end
$upscope $end
$upscope $end
$enddefinitions $end
$comment Show the parameter values. $end
$dumpall
b11 D
b0 C
b10 B
b1 A
$end
#0
$dumpvars
b0 l
b0 k
b0 j
b0 i
b0 h
b0 g
b0 f
b0 e
b0 d
b0 c
b0 b
b0 a
b0 `
b0 _
0^
0]
0\
0[
b0 Z
b0 Y
b0 X
b0 W
b0 V
b1010 U
b0 T
b0 S
b0 R
b0 Q
b0 P
b0 O
b0 N
b0 M
0L
1K
0J
0I
b0 H
b1 G
0F
b0 E
b0 @
b0 ?
b0 >
b0 =
b0 <
0;
b0 :
09
b0 8
07
06
05
b0 4
b0 3
12
01
b0 0
1/
b1010 .
0-
b0 ,
0+
0*
b0 )
b0 (
b0 '
b0 &
b0 %
0$
b0 #
1"
0!
$end
#5000
1!
#10000
0!
#15000
1!
#20000
0!
0"
#25000
1+
1I
0K
0/
b10 G
b1 H
1!
#30000
0!
#35000
1[
1$
1J
0I
0+
b11 G
b1 )
b1 S
b10 H
1!
#40000
0!
#45000
0[
1L
0J
0$
b0 G
b11 H
1!
#50000
0!
#55000
1/
1K
0L
b1 G
b0 H
1!
#60000
0!
#65000
b1 '
b1 O
b1 W
b1 Y
1+
1I
0K
0/
b10 G
b10000000000000000000000000000000000 8
b10000000000000000000000000000000000 M
b1 H
1!
#70000
0!
#75000
1\
1$
1J
0I
0+
b11 G
b10 )
b10 S
b10 H
1!
#80000
0!
#85000
0\
1L
0J
0$
b0 G
b11 H
1!
#90000
0!
#95000
1/
1K
0L
b1 G
b0 H
1!
#100000
0!
#105000
bx .
bx U
b1110 (
b1110 T
b1110 :
b1110 Z
b1110 e
b1110 g
b1110 i
b1110 k
b10 '
b10 O
b10 W
b10 Y
b1110 0
b1110 Q
b1110 R
1+
1I
0K
0/
b10 G
b100000000000000000000000000000001110 8
b100000000000000000000000000000001110 M
b1 H
1!
#110000
0!
#115000
1]
1$
1J
0I
0+
b11 G
b11 )
b11 S
b10 H
1!
#120000
0!
#125000
0]
b1110 3
b1110 ?
02
1L
0J
0$
b0 G
b1110 &
b1110 >
b1110 V
b1110 c
b11 H
b1110 `
b1110 j
1!
#130000
0!
#135000
1/
1K
0L
b1 G
b0 H
1!
#140000
0!
#145000
12
b0 3
b0 ?
b1010 .
b1010 U
b0 &
b0 >
b0 V
b0 c
b0 (
b0 T
b1010 :
b1010 Z
b1010 e
b1010 g
b1010 i
b1010 k
b10001 ,
b10001 @
b10001 P
b11 '
b11 O
b11 W
b11 Y
b1 #
b1 N
b1 X
b0 0
b0 Q
b0 R
1+
1I
0K
0/
b10 G
b100010000110100000000000000000000000000000000 8
b100010000110100000000000000000000000000000000 M
b1 H
1!
#150000
0!
#155000
1^
1$
1J
0I
0+
b11 G
b100 )
b100 S
b10 H
1!
#160000
0!
#165000
0^
b1010 3
b1010 ?
02
1L
0J
0$
b0 G
b1010 &
b1010 >
b1010 V
b1010 c
b11 H
b1010 _
b1010 l
1!
#170000
0!
#175000
1/
1K
0L
b1 G
b0 H
1!
#180000
0!
#185000
b1010 3
b1010 ?
b0 &
b0 >
b0 V
b0 c
b1010 %
b1010 =
b1010 d
b10 ,
b10 @
b10 P
b0 '
b0 O
b0 W
b0 Y
b11 #
b11 N
b11 X
1+
1I
0K
0/
b10 G
b100000001100000000000000000000000000000000 8
b100000001100000000000000000000000000000000 M
b1 H
1!
#190000
0!
#195000
1[
1$
11
1J
0I
0+
b11 G
b101 )
b101 S
b10 H
1!
#200000
0!
#205000
b10100 :
b10100 Z
b10100 e
b10100 g
b10100 i
b10100 k
0[
b10100 3
b10100 ?
1L
0J
01
0$
b0 G
b1010 &
b1010 >
b1010 V
b1010 c
b11 H
b1010 b
b1010 f
1!
#210000
0!
#215000
1/
1K
0L
b1 G
b0 H
1!
#220000
0!
#225000
b100 .
b100 U
b1 (
b1 T
b1 :
b1 Z
b1 e
b1 g
b1 i
b1 k
b0 ,
b0 @
b0 P
b11 '
b11 O
b11 W
b11 Y
b0 #
b0 N
b0 X
b1 0
b1 Q
b1 R
1+
1I
0K
0/
b10 G
b110000000000000000000000000000000001 8
b110000000000000000000000000000000001 M
b1 H
1!
#230000
0!
#235000
1^
1$
1J
0I
0+
b11 G
b110 )
b110 S
b10 H
1!
#240000
0!
#245000
0^
b1011 3
b1011 ?
1L
0J
0$
b0 G
b1 &
b1 >
b1 V
b1 c
b11 H
b1 _
b1 l
1!
#250000
0!
#255000
1/
1K
0L
b1 G
b0 H
1!
#260000
0!
#265000
b1 3
b1 ?
b1010 .
b1010 U
b0 &
b0 >
b0 V
b0 c
b1 %
b1 =
b1 d
b0 (
b0 T
b1 :
b1 Z
b1 e
b1 g
b1 i
b1 k
b10 ,
b10 @
b10 P
b1 '
b1 O
b1 W
b1 Y
b11 #
b11 N
b11 X
b0 0
b0 Q
b0 R
1+
1I
0K
0/
b10 G
b100000011100000000000000000000000000000000 8
b100000011100000000000000000000000000000000 M
b1 H
1!
#270000
0!
#275000
1\
1$
11
1J
0I
0+
b11 G
b111 )
b111 S
b10 H
1!
#280000
0!
#285000
b10 :
b10 Z
b10 e
b10 g
b10 i
b10 k
0\
b10 3
b10 ?
1L
0J
01
0$
b0 G
b1 &
b1 >
b1 V
b1 c
b11 H
b1 a
b1 h
1!
#290000
0!
#295000
1/
1K
0L
b1 G
b0 H
1!
#300000
0!
#305000
b1111 3
b1111 ?
b0 :
b0 Z
b0 e
b0 g
b0 i
b0 k
b1110 %
b1110 =
b1110 d
b111 ,
b111 @
b111 P
b10 #
b10 N
b10 X
1+
1I
0K
0/
b10 G
b1110000011000000000000000000000000000000000 8
b1110000011000000000000000000000000000000000 M
b1 H
1!
#310000
0!
#315000
15
16
b11111111111111111111111111110011 3
b11111111111111111111111111110011 ?
11
b1 4
b1 <
b1 E
1J
0I
0+
b11 G
b1000 )
b1000 S
b10 H
1!
#320000
0!
#325000
05
06
b1111 3
b1111 ?
1L
0J
b0 4
b0 <
b0 E
01
b0 G
19
17
b11 H
1!
#330000
0!
#335000
1/
1K
0L
b1 G
b0 H
1!
#340000
0!
#345000
b10100 3
b10100 ?
b1 .
b1 U
b1010 &
b1010 >
b1010 V
b1010 c
b1010 %
b1010 =
b1010 d
b1010 (
b1010 T
b1001 ,
b1001 @
b1001 P
b0 '
b0 O
b0 W
b0 Y
b0 #
b0 N
b0 X
b1010 0
b1010 Q
b1010 R
1+
1I
0K
0/
b10 G
b10010000000000000000000000000000000000001010 8
b10010000000000000000000000000000000000001010 M
b1 H
1!
#350000
0!
#355000
1J
0I
0+
b11 G
b1001 )
b1001 S
b10 H
1!
#360000
0!
#365000
1L
0J
b0 G
b11 H
1!
#370000
0!
#375000
1/
1K
0L
b1 G
b0 H
1!
#380000
0!
#385000
b11 .
b11 U
b11 (
b11 T
b1000 ,
b1000 @
b1000 P
b11 0
b11 Q
b11 R
1+
1I
0K
0/
b10 G
b10000000000000000000000000000000000000000011 8
b10000000000000000000000000000000000000000011 M
b1 H
1!
#390000
0!
#395000
1*
1J
0I
0+
b11 G
b1010 )
b1010 S
b10 H
1!
#400000
0!
#405000
1L
0J
0*
b0 G
b11 H
b11 )
b11 S
1!
#410000
0!
#415000
1/
1K
0L
b1 G
b0 H
1!
#420000
0!
#425000
b10 3
b10 ?
b100 .
b100 U
b1 &
b1 >
b1 V
b1 c
b1 %
b1 =
b1 d
b1 (
b1 T
b100 :
b100 Z
b100 e
b100 g
b100 i
b100 k
b10001 ,
b10001 @
b10001 P
b11 '
b11 O
b11 W
b11 Y
b1 #
b1 N
b1 X
b0 0
b0 Q
b0 R
1+
1I
0K
0/
b10 G
b100010000110100000000000000000000000000000000 8
b100010000110100000000000000000000000000000000 M
b1 H
1!
#430000
0!
#435000
1^
1$
1J
0I
0+
b11 G
b100 )
b100 S
b10 H
1!
#440000
0!
#445000
0^
b101 3
b101 ?
1L
0J
0$
b0 G
b100 &
b100 >
b100 V
b100 c
b11 H
b100 _
b100 l
1!
#450000
0!
#455000
1/
1K
0L
b1 G
b0 H
1!
#460000
0!
#465000
b1010 .
b1010 U
b0 (
b0 T
b1110 3
b1110 ?
b1110 :
b1110 Z
b1110 e
b1110 g
b1110 i
b1110 k
b1010 &
b1010 >
b1010 V
b1010 c
b100 %
b100 =
b100 d
b10 ,
b10 @
b10 P
b0 '
b0 O
b0 W
b0 Y
b11 #
b11 N
b11 X
1+
1I
0K
0/
b10 G
b100000001100000000000000000000000000000000 8
b100000001100000000000000000000000000000000 M
b1 H
1!
#470000
0!
#475000
1[
1$
11
1J
0I
0+
b11 G
b101 )
b101 S
b10 H
1!
#480000
0!
#485000
b10010 :
b10010 Z
b10010 e
b10010 g
b10010 i
b10010 k
0[
b10010 3
b10010 ?
1L
0J
01
0$
b0 G
b1110 &
b1110 >
b1110 V
b1110 c
09
07
b11 H
b1110 b
b1110 f
1!
#490000
0!
#495000
1/
1K
0L
b1 G
b0 H
1!
#500000
0!
#505000
b10010 3
b10010 ?
b100 .
b100 U
b100 &
b100 >
b100 V
b100 c
b1110 %
b1110 =
b1110 d
b1 (
b1 T
b1 :
b1 Z
b1 e
b1 g
b1 i
b1 k
b0 ,
b0 @
b0 P
b11 '
b11 O
b11 W
b11 Y
b0 #
b0 N
b0 X
b1 0
b1 Q
b1 R
1+
1I
0K
0/
b10 G
b110000000000000000000000000000000001 8
b110000000000000000000000000000000001 M
b1 H
1!
#510000
0!
#515000
1^
1$
1J
0I
0+
b11 G
b110 )
b110 S
b10 H
1!
#520000
0!
#525000
0^
b1111 3
b1111 ?
1L
0J
0$
b0 G
b1 &
b1 >
b1 V
b1 c
b11 H
b1 _
b1 l
1!
#530000
0!
#535000
1/
1K
0L
b1 G
b0 H
1!
#540000
0!
#545000
b10 3
b10 ?
b1010 .
b1010 U
b1 %
b1 =
b1 d
b0 (
b0 T
b10 :
b10 Z
b10 e
b10 g
b10 i
b10 k
b10 ,
b10 @
b10 P
b1 '
b1 O
b1 W
b1 Y
b11 #
b11 N
b11 X
b0 0
b0 Q
b0 R
1+
1I
0K
0/
b10 G
b100000011100000000000000000000000000000000 8
b100000011100000000000000000000000000000000 M
b1 H
1!
#550000
0!
#555000
1\
1$
11
1J
0I
0+
b11 G
b111 )
b111 S
b10 H
1!
#560000
0!
#565000
b11 :
b11 Z
b11 e
b11 g
b11 i
b11 k
0\
b11 3
b11 ?
1L
0J
01
0$
b0 G
b10 &
b10 >
b10 V
b10 c
b11 H
b10 a
b10 h
1!
#570000
0!
#575000
1/
1K
0L
b1 G
b0 H
1!
#580000
0!
#585000
b10000 3
b10000 ?
b0 :
b0 Z
b0 e
b0 g
b0 i
b0 k
b1110 %
b1110 =
b1110 d
b111 ,
b111 @
b111 P
b10 #
b10 N
b10 X
1+
1I
0K
0/
b10 G
b1110000011000000000000000000000000000000000 8
b1110000011000000000000000000000000000000000 M
b1 H
1!
#590000
0!
#595000
15
16
b11111111111111111111111111110100 3
b11111111111111111111111111110100 ?
11
b1 4
b1 <
b1 E
1J
0I
0+
b11 G
b1000 )
b1000 S
b10 H
1!
#600000
0!
#605000
05
06
b10000 3
b10000 ?
1L
0J
b0 4
b0 <
b0 E
01
b0 G
19
17
b11 H
1!
#610000
0!
#615000
1/
1K
0L
b1 G
b0 H
1!
#620000
0!
#625000
b11100 3
b11100 ?
b1 .
b1 U
b1110 &
b1110 >
b1110 V
b1110 c
b1010 (
b1010 T
b1001 ,
b1001 @
b1001 P
b0 '
b0 O
b0 W
b0 Y
b0 #
b0 N
b0 X
b1010 0
b1010 Q
b1010 R
1+
1I
0K
0/
b10 G
b10010000000000000000000000000000000000001010 8
b10010000000000000000000000000000000000001010 M
b1 H
1!
#630000
0!
#635000
1J
0I
0+
b11 G
b1001 )
b1001 S
b10 H
1!
#640000
0!
#645000
1L
0J
b0 G
b11 H
1!
#650000
0!
#655000
1/
1K
0L
b1 G
b0 H
1!
#660000
0!
#665000
b11 .
b11 U
b11 (
b11 T
b1000 ,
b1000 @
b1000 P
b11 0
b11 Q
b11 R
1+
1I
0K
0/
b10 G
b10000000000000000000000000000000000000000011 8
b10000000000000000000000000000000000000000011 M
b1 H
1!
#670000
0!
#675000
1*
1J
0I
0+
b11 G
b1010 )
b1010 S
b10 H
1!
#680000
0!
#685000
1L
0J
0*
b0 G
b11 H
b11 )
b11 S
1!
#690000
0!
#695000
1/
1K
0L
b1 G
b0 H
1!
#700000
0!
#705000
b11 3
b11 ?
b110 .
b110 U
b1 &
b1 >
b1 V
b1 c
b10 %
b10 =
b10 d
b10 (
b10 T
b110 :
b110 Z
b110 e
b110 g
b110 i
b110 k
b10001 ,
b10001 @
b10001 P
b11 '
b11 O
b11 W
b11 Y
b1 #
b1 N
b1 X
b0 0
b0 Q
b0 R
1+
1I
0K
0/
b10 G
b100010000110100000000000000000000000000000000 8
b100010000110100000000000000000000000000000000 M
b1 H
1!
#710000
0!
#715000
1^
1$
1J
0I
0+
b11 G
b100 )
b100 S
b10 H
1!
#720000
0!
#725000
0^
b1000 3
b1000 ?
1L
0J
0$
b0 G
b110 &
b110 >
b110 V
b110 c
b11 H
b110 _
b110 l
1!
#730000
0!
#735000
1/
1K
0L
b1 G
b0 H
1!
#740000
0!
#745000
b1010 .
b1010 U
b0 (
b0 T
b10100 3
b10100 ?
b10100 :
b10100 Z
b10100 e
b10100 g
b10100 i
b10100 k
b1110 &
b1110 >
b1110 V
b1110 c
b110 %
b110 =
b110 d
b10 ,
b10 @
b10 P
b0 '
b0 O
b0 W
b0 Y
b11 #
b11 N
b11 X
1+
1I
0K
0/
b10 G
b100000001100000000000000000000000000000000 8
b100000001100000000000000000000000000000000 M
b1 H
1!
#750000
0!
#755000
1[
1$
11
1J
0I
0+
b11 G
b101 )
b101 S
b10 H
1!
#760000
0!
#765000
b11010 :
b11010 Z
b11010 e
b11010 g
b11010 i
b11010 k
0[
b11010 3
b11010 ?
1L
0J
01
0$
b0 G
b10100 &
b10100 >
b10100 V
b10100 c
09
07
b11 H
b10100 b
b10100 f
1!
#770000
0!
#775000
1/
1K
0L
b1 G
b0 H
1!
#780000
0!
